MANIFEST.in
setup.py
Glosarium.egg-info/PKG-INFO
Glosarium.egg-info/SOURCES.txt
Glosarium.egg-info/dependency_links.txt
Glosarium.egg-info/entry_points.txt
Glosarium.egg-info/not-zip-safe
Glosarium.egg-info/requires.txt
Glosarium.egg-info/top_level.txt
glosarium/__init__.py
glosarium/glosary_parser.py
glosarium/po_parser.py
glosarium/scripts/__init__.py
glosarium/scripts/main.py
glosarium/test/__init__.py
glosarium/test/test_glosarium.py
glosarium/test/test_glosary_parser.py
glosarium/test/test_po_parser.py