Metadata-Version: 1.1
Name: Glosarium
Version: 1.2
Summary: Glosarium parser
Home-page: http://www.gnu.org/server/standards/transaltions/es/index.html
Author: Oscar Campos
Author-email: oscar.campos@member.fsf.org
License: GPL
Platform: UNKNOWN
Classifier: Programming Language :: Python :: 2.6
Classifier: Development Status :: 4 - Beta
Classifier: Environment :: Console
Classifier: Intended Audience :: End Users/Desktop
Classifier: License :: OSI Approved :: GNU General Public License v3 (GPLv3)
Classifier: Operating System :: POSIX :: Linux
Classifier: Operating System :: Unix
Classifier: Topic :: Text Processing :: Linguistic
Requires: httplib2(>=0.6)
